{
  "updated": "2026-04-22T06:27:16Z",
  "data": {
    "sp": {
      "price": 7064.01,
      "chgPct": -0.63,
      "src": "GHA"
    },
    "ndq": {
      "price": 24259.96,
      "chgPct": -0.59,
      "src": "GHA"
    },
    "dji": {
      "price": 49149.38,
      "chgPct": -0.59,
      "src": "GHA"
    },
    "inr": {
      "price": 93.8,
      "chgPct": 0.34,
      "src": "GHA"
    },
    "crude": {
      "price": 88.85,
      "chgPct": -0.58,
      "src": "GHA"
    },
    "gold": {
      "price": 4781.9,
      "chgPct": 0.1,
      "src": "GHA"
    },
    "silver": {
      "price": 78.38,
      "chgPct": 0.37,
      "src": "GHA"
    },
    "n50": {
      "price": 24415.15,
      "chgPct": -0.67,
      "src": "GHA"
    },
    "bn": {
      "price": 57361.5,
      "chgPct": 0.02,
      "src": "GHA"
    },
    "sx": {
      "price": 78699.69,
      "chgPct": -0.72,
      "src": "GHA"
    },
    "fn": {
      "price": 26698.3,
      "chgPct": -0.52,
      "src": "GHA"
    },
    "vix": {
      "price": 18.17,
      "chgPct": 3.43,
      "src": "GHA"
    },
    "t_RELIANCE": {
      "price": 1363.2,
      "chgPct": 0.73,
      "src": "GHA"
    },
    "t_HDFCBANK": {
      "price": 803.95,
      "chgPct": -0.99,
      "src": "GHA"
    },
    "t_ICICIBANK": {
      "price": 1370.6,
      "chgPct": -1.28,
      "src": "GHA"
    },
    "t_INFY": {
      "price": 1258.9,
      "chgPct": -4.24,
      "src": "GHA"
    },
    "t_TCS": {
      "price": 2532.3,
      "chgPct": -2.97,
      "src": "GHA"
    },
    "t_AIRTEL": {
      "price": 1840.6,
      "chgPct": -0.78,
      "src": "GHA"
    },
    "t_ITC": {
      "price": 306.65,
      "chgPct": -1.08,
      "src": "GHA"
    },
    "t_SBI": {
      "price": 1105.2,
      "chgPct": -0.57,
      "src": "GHA"
    },
    "t_KOTAK": {
      "price": 378.3,
      "chgPct": -1.01,
      "src": "GHA"
    },
    "t_LT": {
      "price": 4028.0,
      "chgPct": -1.16,
      "src": "GHA"
    },
    "u_AAPL": {
      "price": 266.17,
      "chgPct": -1.96,
      "src": "GHA"
    },
    "u_MSFT": {
      "price": 424.16,
      "chgPct": 1.5,
      "src": "GHA"
    },
    "u_NVDA": {
      "price": 199.88,
      "chgPct": -0.91,
      "src": "GHA"
    },
    "u_AMZN": {
      "price": 249.91,
      "chgPct": -1.73,
      "src": "GHA"
    },
    "u_GOOGL": {
      "price": 332.29,
      "chgPct": -1.69,
      "src": "GHA"
    },
    "u_META": {
      "price": 668.84,
      "chgPct": -0.53,
      "src": "GHA"
    },
    "u_TSLA": {
      "price": 386.42,
      "chgPct": -1.53,
      "src": "GHA"
    },
    "u_BRK": {
      "price": 468.5,
      "chgPct": -0.95,
      "src": "GHA"
    },
    "u_JPM": {
      "price": 313.0,
      "chgPct": -1.46,
      "src": "GHA"
    },
    "u_UNH": {
      "price": 346.01,
      "chgPct": 6.46,
      "src": "GHA"
    }
  },
  "errors": []
}