{
  "updated": "2026-05-26T16:33:40Z",
  "data": {
    "sp": {
      "price": 7516.81,
      "chgPct": 0.57,
      "src": "GHA"
    },
    "ndq": {
      "price": 26611.2,
      "chgPct": 1.01,
      "src": "GHA"
    },
    "dji": {
      "price": 50489.49,
      "chgPct": -0.19,
      "src": "GHA"
    },
    "inr": {
      "price": 95.67,
      "chgPct": 0.47,
      "src": "GHA"
    },
    "crude": {
      "price": 94.22,
      "chgPct": -2.46,
      "src": "GHA"
    },
    "gold": {
      "price": 4505.7,
      "chgPct": -0.39,
      "src": "GHA"
    },
    "silver": {
      "price": 76.39,
      "chgPct": 0.26,
      "src": "GHA"
    },
    "n50": {
      "price": 23913.7,
      "chgPct": -0.57,
      "src": "GHA"
    },
    "bn": {
      "price": 55092.9,
      "chgPct": -0.54,
      "src": "GHA"
    },
    "sx": {
      "price": 76009.7,
      "chgPct": -0.63,
      "src": "GHA"
    },
    "fn": {
      "price": 25932.25,
      "chgPct": -0.8,
      "src": "GHA"
    },
    "vix": {
      "price": 16.13,
      "chgPct": -2.26,
      "src": "GHA"
    },
    "t_RELIANCE": {
      "price": 1356.3,
      "chgPct": -0.75,
      "src": "GHA"
    },
    "t_HDFCBANK": {
      "price": 778.9,
      "chgPct": -1.04,
      "src": "GHA"
    },
    "t_ICICIBANK": {
      "price": 1279.1,
      "chgPct": -0.98,
      "src": "GHA"
    },
    "t_INFY": {
      "price": 1167.7,
      "chgPct": -0.03,
      "src": "GHA"
    },
    "t_TCS": {
      "price": 2276.2,
      "chgPct": -1.38,
      "src": "GHA"
    },
    "t_AIRTEL": {
      "price": 1846.9,
      "chgPct": -1.49,
      "src": "GHA"
    },
    "t_ITC": {
      "price": 301.65,
      "chgPct": -0.84,
      "src": "GHA"
    },
    "t_SBI": {
      "price": 968.5,
      "chgPct": -0.36,
      "src": "GHA"
    },
    "t_KOTAK": {
      "price": 388.65,
      "chgPct": -1.18,
      "src": "GHA"
    },
    "t_LT": {
      "price": 4037.8,
      "chgPct": 0.08,
      "src": "GHA"
    },
    "u_AAPL": {
      "price": 310.6,
      "chgPct": 0.71,
      "src": "GHA"
    },
    "u_MSFT": {
      "price": 416.1,
      "chgPct": -0.41,
      "src": "GHA"
    },
    "u_NVDA": {
      "price": 213.34,
      "chgPct": -0.45,
      "src": "GHA"
    },
    "u_AMZN": {
      "price": 264.14,
      "chgPct": -0.47,
      "src": "GHA"
    },
    "u_GOOGL": {
      "price": 387.1,
      "chgPct": 1.26,
      "src": "GHA"
    },
    "u_META": {
      "price": 610.76,
      "chgPct": 0.56,
      "src": "GHA"
    },
    "u_TSLA": {
      "price": 430.73,
      "chgPct": 1.66,
      "src": "GHA"
    },
    "u_BRK": {
      "price": 484.66,
      "chgPct": -0.18,
      "src": "GHA"
    },
    "u_JPM": {
      "price": 306.99,
      "chgPct": 0.65,
      "src": "GHA"
    },
    "u_UNH": {
      "price": 378.07,
      "chgPct": -2.29,
      "src": "GHA"
    }
  },
  "errors": []
}