{
  "updated": "2026-04-24T08:55:39Z",
  "data": {
    "sp": {
      "price": 7108.4,
      "chgPct": -0.41,
      "src": "GHA"
    },
    "ndq": {
      "price": 24438.5,
      "chgPct": -0.89,
      "src": "GHA"
    },
    "dji": {
      "price": 49310.32,
      "chgPct": -0.36,
      "src": "GHA"
    },
    "inr": {
      "price": 94.28,
      "chgPct": 0.21,
      "src": "GHA"
    },
    "crude": {
      "price": 97.41,
      "chgPct": 0.82,
      "src": "GHA"
    },
    "gold": {
      "price": 4703.7,
      "chgPct": 0.35,
      "src": "GHA"
    },
    "silver": {
      "price": 74.68,
      "chgPct": -0.17,
      "src": "GHA"
    },
    "n50": {
      "price": 23858.9,
      "chgPct": -1.23,
      "src": "GHA"
    },
    "bn": {
      "price": 55869.15,
      "chgPct": -0.79,
      "src": "GHA"
    },
    "sx": {
      "price": 76479.73,
      "chgPct": -1.53,
      "src": "GHA"
    },
    "fn": {
      "price": 26064.2,
      "chgPct": -0.68,
      "src": "GHA"
    },
    "vix": {
      "price": 19.58,
      "chgPct": 5.53,
      "src": "GHA"
    },
    "t_RELIANCE": {
      "price": 1328.1,
      "chgPct": -1.21,
      "src": "GHA"
    },
    "t_HDFCBANK": {
      "price": 781.8,
      "chgPct": -0.27,
      "src": "GHA"
    },
    "t_ICICIBANK": {
      "price": 1327.5,
      "chgPct": -1.52,
      "src": "GHA"
    },
    "t_INFY": {
      "price": 1155.1,
      "chgPct": -6.14,
      "src": "GHA"
    },
    "t_TCS": {
      "price": 2396.9,
      "chgPct": -4.77,
      "src": "GHA"
    },
    "t_AIRTEL": {
      "price": 1807.4,
      "chgPct": -1.85,
      "src": "GHA"
    },
    "t_ITC": {
      "price": 302.25,
      "chgPct": -1.02,
      "src": "GHA"
    },
    "t_SBI": {
      "price": 1098.5,
      "chgPct": 0.27,
      "src": "GHA"
    },
    "t_KOTAK": {
      "price": 368.85,
      "chgPct": -0.7,
      "src": "GHA"
    },
    "t_LT": {
      "price": 4002.3,
      "chgPct": -1.28,
      "src": "GHA"
    },
    "u_AAPL": {
      "price": 273.43,
      "chgPct": 0.27,
      "src": "GHA"
    },
    "u_MSFT": {
      "price": 415.75,
      "chgPct": -0.69,
      "src": "GHA"
    },
    "u_NVDA": {
      "price": 199.64,
      "chgPct": 0.07,
      "src": "GHA"
    },
    "u_AMZN": {
      "price": 255.08,
      "chgPct": -0.07,
      "src": "GHA"
    },
    "u_GOOGL": {
      "price": 338.89,
      "chgPct": -0.25,
      "src": "GHA"
    },
    "u_META": {
      "price": 659.15,
      "chgPct": -0.23,
      "src": "GHA"
    },
    "u_TSLA": {
      "price": 373.72,
      "chgPct": 0.14,
      "src": "GHA"
    },
    "u_BRK": {
      "price": 470.55,
      "chgPct": -0.02,
      "src": "GHA"
    },
    "u_JPM": {
      "price": 311.69,
      "chgPct": 0.21,
      "src": "GHA"
    },
    "u_UNH": {
      "price": 354.56,
      "chgPct": 0.06,
      "src": "GHA"
    }
  },
  "errors": []
}